README.rst
setup.cfg
setup.py
turtlepaint.py
turtlepaint.egg-info/PKG-INFO
turtlepaint.egg-info/SOURCES.txt
turtlepaint.egg-info/dependency_links.txt
turtlepaint.egg-info/top_level.txt