Metadata-Version: 1.0
Name: turtlepaint
Version: 0.0.1
Summary: Program for drawing things with turtle.
Home-page: UNKNOWN
Author: Superloach
Author-email: UNKNOWN
License: UNKNOWN
Keywords: turtle draw paint graphics
Platform: UNKNOWN
